<Matrikon.OPC.Modbus><CModRootDevLink name="" description="Modbus Root DevLink"><CModEthPlcDevLink name="STAN1" description="Stop, Finish, Help, Axes of STAN 1" host="192.168.21.2" port="502" address="1" timeout="300" retries="3" reconnectDelay="10000" maxRegs="0"/><CModEthPlcDevLink name="STAN2" description="Stop, Finish, Help of STAN 2" host="192.168.22.2" port="502" address="1" timeout="300" retries="3" reconnectDelay="10000" maxRegs="0"/><CModEthPlcDevLink name="STAN2_2" description="Stop, Finish, Help of STAN 2.2" host="192.168.29.2" port="502" address="1" timeout="300" retries="3" reconnectDelay="10000" maxRegs="0"/><CModEthPlcDevLink name="STAN3" description="Stop, Finish, Help of STAN 3" host="192.168.23.2" port="502" address="1" timeout="300" retries="3" reconnectDelay="10000" maxRegs="0"/><CModEthPlcDevLink name="STAN4" description="Stop, Finish, Help of STAN 4" host="192.168.24.2" port="502" address="1" timeout="300" retries="3" reconnectDelay="10000" maxRegs="0"/><CModEthPlcDevLink name="STAN5" description="Stop, Finish, Help of STAN 5" host="192.168.25.2" port="502" address="1" timeout="300" retries="3" reconnectDelay="10000" maxRegs="0"/><CModEthPlcDevLink name="STAN6" description="Stop, Finish, Help of STAN 6" host="192.168.26.2" port="502" address="1" timeout="300" retries="3" reconnectDelay="10000" maxRegs="0"/><CModEthPlcDevLink name="STAN7" description="Stop, Finish, Help of STAN 7" host="192.168.27.2" port="502" address="1" timeout="300" retries="3" reconnectDelay="10000" maxRegs="0"/><CModEthPlcDevLink name="STAN8" description="Stop, Finish, Help of STAN 8" host="192.168.28.2" port="502" address="1" timeout="300" retries="3" reconnectDelay="10000" maxRegs="0"/><CModEthPlcDevLink name="STAN_FA5A" description="Stop, Finish, Help of STAN 5.A" host="192.168.30.2" port="502" address="1" timeout="300" retries="3" reconnectDelay="10000" maxRegs="0"/><CModEthPlcDevLink name="STAN_FI" description="Stop, Finish, Help of STAN FI" host="192.168.31.2" port="502" address="1" timeout="300" retries="3" reconnectDelay="10000" maxRegs="0"/><CModEthPlcDevLink name="STAN_PDI1" description="Stop, Finish, Help of PDI1" host="192.168.33.2" port="502" address="1" timeout="300" retries="3" reconnectDelay="10000" maxRegs="0"/><CModEthPlcDevLink name="STAN_PDI2" description="Stop, Finish, Help of PDI2" host="192.168.34.2" port="502" address="1" timeout="300" retries="3" reconnectDelay="10000" maxRegs="0"/><CModEthPlcDevLink name="STAN_TIP" description="Stop, Finish, Help of STAN TIP" host="192.168.32.2" port="502" address="1" timeout="300" retries="3" reconnectDelay="10000" maxRegs="0"/></CModRootDevLink><PSTAliasGroup><PSTAliasGroup name="STAN1"><PSTAlias name="Fail" itemPath="STAN1.1:6" type="1" dataType="11"><Scaling enabled="0" type="0"/><Events enabled="0" source="Alias" severity="1" trigger="0" timestamp="0"/></PSTAlias><PSTAlias name="Fail_s" itemPath="STAN1.0:6" type="1" dataType="11"><Scaling enabled="0" type="0"/><Events enabled="0" source="Alias" severity="1" trigger="0" timestamp="0"/></PSTAlias><PSTAlias name="Finish" itemPath="STAN1.1:3" type="1" dataType="11"><Scaling enabled="0" type="0"/><Events enabled="0" source="Alias" severity="1" trigger="0" timestamp="0"/></PSTAlias><PSTAlias name="Finish_s" itemPath="STAN1.0:3" type="1" dataType="11"><Scaling enabled="0" type="0"/><Events enabled="0" source="Alias" severity="1" trigger="0" timestamp="0"/></PSTAlias><PSTAlias name="Help" itemPath="STAN1.1:2" type="1" dataType="11"><Scaling enabled="0" type="0"/><Events enabled="0" source="Alias" severity="1" trigger="0" timestamp="0"/></PSTAlias><PSTAlias name="Help_s" itemPath="STAN1.0:2" type="1" dataType="11"><Scaling enabled="0" type="0"/><Events enabled="0" source="Alias" severity="1" trigger="0" timestamp="0"/></PSTAlias><PSTAlias name="Part1" itemPath="STAN1.1:4" type="1" dataType="11"><Scaling enabled="0" type="0"/><Events enabled="0" source="Alias" severity="1" trigger="0" timestamp="0"/></PSTAlias><PSTAlias name="Part1_s" itemPath="STAN1.0:4" type="1" dataType="11"><Scaling enabled="0" type="0"/><Events enabled="0" source="Alias" severity="1" trigger="0" timestamp="0"/></PSTAlias><PSTAlias name="Part2" itemPath="STAN1.1:5" type="1" dataType="11"><Scaling enabled="0" type="0"/><Events enabled="0" source="Alias" severity="1" trigger="0" timestamp="0"/></PSTAlias><PSTAlias name="Part2_s" itemPath="STAN1.0:5" type="1" dataType="11"><Scaling enabled="0" type="0"/><Events enabled="0" source="Alias" severity="1" trigger="0" timestamp="0"/></PSTAlias><PSTAlias name="Stop" itemPath="STAN1.1:1" type="1" dataType="11"><Scaling enabled="0" type="0"/><Events enabled="0" source="Alias" severity="1" trigger="0" timestamp="0"/></PSTAlias><PSTAlias name="Stop_s" itemPath="STAN1.0:1" type="1" dataType="11"><Scaling enabled="0" type="0"/><Events enabled="0" source="Alias" severity="1" trigger="0" timestamp="0"/></PSTAlias></PSTAliasGroup><PSTAliasGroup name="STAN2"><PSTAlias name="Fail" itemPath="STAN2.1:26" type="1" dataType="11"><Scaling enabled="0" type="0"/><Events enabled="0" source="Alias" severity="1" trigger="0" timestamp="0"/></PSTAlias><PSTAlias name="Fail_s" itemPath="STAN2.0:26" type="1" dataType="11"><Scaling enabled="0" type="0"/><Events enabled="0" source="Alias" severity="1" trigger="0" timestamp="0"/></PSTAlias><PSTAlias name="Finish" itemPath="STAN2.1:23" type="1" dataType="11"><Scaling enabled="0" type="0"/><Events enabled="0" source="Alias" severity="1" trigger="0" timestamp="0"/></PSTAlias><PSTAlias name="Finish_s" itemPath="STAN2.0:23" type="1" dataType="11"><Scaling enabled="0" type="0"/><Events enabled="0" source="Alias" severity="1" trigger="0" timestamp="0"/></PSTAlias><PSTAlias name="Help" itemPath="STAN2.1:22" type="1" dataType="11"><Scaling enabled="0" type="0"/><Events enabled="0" source="Alias" severity="1" trigger="0" timestamp="0"/></PSTAlias><PSTAlias name="Help_s" itemPath="STAN2.0:22" type="1" dataType="11"><Scaling enabled="0" type="0"/><Events enabled="0" source="Alias" severity="1" trigger="0" timestamp="0"/></PSTAlias><PSTAlias name="Part1" itemPath="STAN2.1:24" type="1" dataType="11"><Scaling enabled="0" type="0"/><Events enabled="0" source="Alias" severity="1" trigger="0" timestamp="0"/></PSTAlias><PSTAlias name="Part1_s" itemPath="STAN2.0:24" type="1" dataType="11"><Scaling enabled="0" type="0"/><Events enabled="0" source="Alias" severity="1" trigger="0" timestamp="0"/></PSTAlias><PSTAlias name="Part2" itemPath="STAN2.1:25" type="1" dataType="11"><Scaling enabled="0" type="0"/><Events enabled="0" source="Alias" severity="1" trigger="0" timestamp="0"/></PSTAlias><PSTAlias name="Part2_s" itemPath="STAN2.0:25" type="1" dataType="11"><Scaling enabled="0" type="0"/><Events enabled="0" source="Alias" severity="1" trigger="0" timestamp="0"/></PSTAlias><PSTAlias name="Stop" itemPath="STAN2.1:21" type="1" dataType="11"><Scaling enabled="0" type="0"/><Events enabled="0" source="Alias" severity="1" trigger="0" timestamp="0"/></PSTAlias><PSTAlias name="Stop_s" itemPath="STAN2.0:21" type="1" dataType="11"><Scaling enabled="0" type="0"/><Events enabled="0" source="Alias" severity="1" trigger="0" timestamp="0"/></PSTAlias></PSTAliasGroup><PSTAliasGroup name="STAN2_2"><PSTAlias name="Fail" itemPath="STAN2_2.1:6" type="1" dataType="11"><Scaling enabled="0" type="0"/><Events enabled="0" source="Alias" severity="1" trigger="0" timestamp="0"/></PSTAlias><PSTAlias name="Fail_s" itemPath="STAN2_2.0:6" type="1" dataType="11"><Scaling enabled="0" type="0"/><Events enabled="0" source="Alias" severity="1" trigger="0" timestamp="0"/></PSTAlias><PSTAlias name="Finish" itemPath="STAN2_2.1:3" type="1" dataType="11"><Scaling enabled="0" type="0"/><Events enabled="0" source="Alias" severity="1" trigger="0" timestamp="0"/></PSTAlias><PSTAlias name="Finish_s" itemPath="STAN2_2.0:3" type="1" dataType="11"><Scaling enabled="0" type="0"/><Events enabled="0" source="Alias" severity="1" trigger="0" timestamp="0"/></PSTAlias><PSTAlias name="Help" itemPath="STAN2_2.1:2" type="1" dataType="11"><Scaling enabled="0" type="0"/><Events enabled="0" source="Alias" severity="1" trigger="0" timestamp="0"/></PSTAlias><PSTAlias name="Help_s" itemPath="STAN2_2.0:2" type="1" dataType="11"><Scaling enabled="0" type="0"/><Events enabled="0" source="Alias" severity="1" trigger="0" timestamp="0"/></PSTAlias><PSTAlias name="Part1" itemPath="STAN2_2.1:4" type="1" dataType="11"><Scaling enabled="0" type="0"/><Events enabled="0" source="Alias" severity="1" trigger="0" timestamp="0"/></PSTAlias><PSTAlias name="Part1_s" itemPath="STAN2_2.0:4" type="1" dataType="11"><Scaling enabled="0" type="0"/><Events enabled="0" source="Alias" severity="1" trigger="0" timestamp="0"/></PSTAlias><PSTAlias name="Part2" itemPath="STAN2_2.1:5" type="1" dataType="11"><Scaling enabled="0" type="0"/><Events enabled="0" source="Alias" severity="1" trigger="0" timestamp="0"/></PSTAlias><PSTAlias name="Part2_s" itemPath="STAN2_2.0:5" type="1" dataType="11"><Scaling enabled="0" type="0"/><Events enabled="0" source="Alias" severity="1" trigger="0" timestamp="0"/></PSTAlias><PSTAlias name="Stop" itemPath="STAN2_2.1:1" type="1" dataType="11"><Scaling enabled="0" type="0"/><Events enabled="0" source="Alias" severity="1" trigger="0" timestamp="0"/></PSTAlias><PSTAlias name="Stop_s" itemPath="STAN2_2.0:1" type="1" dataType="11"><Scaling enabled="0" type="0"/><Events enabled="0" source="Alias" severity="1" trigger="0" timestamp="0"/></PSTAlias></PSTAliasGroup><PSTAliasGroup name="STAN3"><PSTAlias name="Fail" itemPath="STAN3.1:26" type="1" dataType="11"><Scaling enabled="0" type="0"/><Events enabled="0" source="Alias" severity="1" trigger="0" timestamp="0"/></PSTAlias><PSTAlias name="Fail_s" itemPath="STAN3.0:26" type="1" dataType="11"><Scaling enabled="0" type="0"/><Events enabled="0" source="Alias" severity="1" trigger="0" timestamp="0"/></PSTAlias><PSTAlias name="Finish" itemPath="STAN3.1:23" type="1" dataType="11"><Scaling enabled="0" type="0"/><Events enabled="0" source="Alias" severity="1" trigger="0" timestamp="0"/></PSTAlias><PSTAlias name="Finish_s" itemPath="STAN3.0:23" type="1" dataType="11"><Scaling enabled="0" type="0"/><Events enabled="0" source="Alias" severity="1" trigger="0" timestamp="0"/></PSTAlias><PSTAlias name="Help" itemPath="STAN3.1:22" type="1" dataType="11" updateRate="200"><Scaling enabled="0" type="0"/><Events enabled="0" source="Alias" severity="1" trigger="0" timestamp="0"/></PSTAlias><PSTAlias name="Help_s" itemPath="STAN3.0:22" type="1" dataType="11" updateRate="200"><Scaling enabled="0" type="0"/><Events enabled="0" source="Alias" severity="1" trigger="0" timestamp="0"/></PSTAlias><PSTAlias name="Part1" itemPath="STAN3.1:24" type="1" dataType="11"><Scaling enabled="0" type="0"/><Events enabled="0" source="Alias" severity="1" trigger="0" timestamp="0"/></PSTAlias><PSTAlias name="Part1_s" itemPath="STAN3.0:24" type="1" dataType="11"><Scaling enabled="0" type="0"/><Events enabled="0" source="Alias" severity="1" trigger="0" timestamp="0"/></PSTAlias><PSTAlias name="Part2" itemPath="STAN3.1:25" type="1" dataType="11"><Scaling enabled="0" type="0"/><Events enabled="0" source="Alias" severity="1" trigger="0" timestamp="0"/></PSTAlias><PSTAlias name="Part2_s" itemPath="STAN3.0:25" type="1" dataType="11"><Scaling enabled="0" type="0"/><Events enabled="0" source="Alias" severity="1" trigger="0" timestamp="0"/></PSTAlias><PSTAlias name="Stop" itemPath="STAN3.1:21" type="1" dataType="11" updateRate="100"><Scaling enabled="0" type="0"/><Events enabled="0" source="Alias" severity="1" trigger="0" timestamp="0"/></PSTAlias><PSTAlias name="Stop_s" itemPath="STAN3.0:21" type="1" dataType="11" updateRate="100"><Scaling enabled="0" type="0"/><Events enabled="0" source="Alias" severity="1" trigger="0" timestamp="0"/></PSTAlias></PSTAliasGroup><PSTAliasGroup name="STAN4"><PSTAlias name="Fail" itemPath="STAN4.1:26" type="1" dataType="11"><Scaling enabled="0" type="0"/><Events enabled="0" source="Alias" severity="1" trigger="0" timestamp="0"/></PSTAlias><PSTAlias name="Fail_s" itemPath="STAN4.0:26" type="1" dataType="11"><Scaling enabled="0" type="0"/><Events enabled="0" source="Alias" severity="1" trigger="0" timestamp="0"/></PSTAlias><PSTAlias name="Finish" itemPath="STAN4.1:23" type="1" dataType="11"><Scaling enabled="0" type="0"/><Events enabled="0" source="Alias" severity="1" trigger="0" timestamp="0"/></PSTAlias><PSTAlias name="Finish_s" itemPath="STAN4.0:23" type="1" dataType="11"><Scaling enabled="0" type="0"/><Events enabled="0" source="Alias" severity="1" trigger="0" timestamp="0"/></PSTAlias><PSTAlias name="Help" itemPath="STAN4.1:22" type="1" dataType="11"><Scaling enabled="0" type="0"/><Events enabled="0" source="Alias" severity="1" trigger="0" timestamp="0"/></PSTAlias><PSTAlias name="Help_s" itemPath="STAN4.0:22" type="1" dataType="11"><Scaling enabled="0" type="0"/><Events enabled="0" source="Alias" severity="1" trigger="0" timestamp="0"/></PSTAlias><PSTAlias name="Part1" itemPath="STAN4.1:24" type="1" dataType="11"><Scaling enabled="0" type="0"/><Events enabled="0" source="Alias" severity="1" trigger="0" timestamp="0"/></PSTAlias><PSTAlias name="Part1_s" itemPath="STAN4.0:24" type="1" dataType="11"><Scaling enabled="0" type="0"/><Events enabled="0" source="Alias" severity="1" trigger="0" timestamp="0"/></PSTAlias><PSTAlias name="Part2" itemPath="STAN4.1:25" type="1" dataType="11"><Scaling enabled="0" type="0"/><Events enabled="0" source="Alias" severity="1" trigger="0" timestamp="0"/></PSTAlias><PSTAlias name="Part2_s" itemPath="STAN4.0:25" type="1" dataType="11"><Scaling enabled="0" type="0"/><Events enabled="0" source="Alias" severity="1" trigger="0" timestamp="0"/></PSTAlias><PSTAlias name="Stop" itemPath="STAN4.1:21" type="1" dataType="11"><Scaling enabled="0" type="0"/><Events enabled="0" source="Alias" severity="1" trigger="0" timestamp="0"/></PSTAlias><PSTAlias name="Stop_s" itemPath="STAN4.0:21" type="1" dataType="11"><Scaling enabled="0" type="0"/><Events enabled="0" source="Alias" severity="1" trigger="0" timestamp="0"/></PSTAlias></PSTAliasGroup><PSTAliasGroup name="STAN5"><PSTAlias name="Fail" itemPath="STAN5.1:6" type="1" dataType="11"><Scaling enabled="0" type="0"/><Events enabled="0" source="Alias" severity="1" trigger="0" timestamp="0"/></PSTAlias><PSTAlias name="Fail_s" itemPath="STAN5.0:6" type="1" dataType="11"><Scaling enabled="0" type="0"/><Events enabled="0" source="Alias" severity="1" trigger="0" timestamp="0"/></PSTAlias><PSTAlias name="Finish" itemPath="STAN5.1:3" type="1" dataType="11"><Scaling enabled="0" type="0"/><Events enabled="0" source="Alias" severity="1" trigger="0" timestamp="0"/></PSTAlias><PSTAlias name="Finish_s" itemPath="STAN5.0:3" type="1" dataType="11"><Scaling enabled="0" type="0"/><Events enabled="0" source="Alias" severity="1" trigger="0" timestamp="0"/></PSTAlias><PSTAlias name="Help" itemPath="STAN5.1:2" type="1" dataType="11"><Scaling enabled="0" type="0"/><Events enabled="0" source="Alias" severity="1" trigger="0" timestamp="0"/></PSTAlias><PSTAlias name="Help_s" itemPath="STAN5.0:2" type="1" dataType="11"><Scaling enabled="0" type="0"/><Events enabled="0" source="Alias" severity="1" trigger="0" timestamp="0"/></PSTAlias><PSTAlias name="Part1" itemPath="STAN5.1:4" type="1" dataType="11"><Scaling enabled="0" type="0"/><Events enabled="0" source="Alias" severity="1" trigger="0" timestamp="0"/></PSTAlias><PSTAlias name="Part1_s" itemPath="STAN5.0:4" type="1" dataType="11"><Scaling enabled="0" type="0"/><Events enabled="0" source="Alias" severity="1" trigger="0" timestamp="0"/></PSTAlias><PSTAlias name="Part2" itemPath="STAN5.1:5" type="1" dataType="11"><Scaling enabled="0" type="0"/><Events enabled="0" source="Alias" severity="1" trigger="0" timestamp="0"/></PSTAlias><PSTAlias name="Part2_s" itemPath="STAN5.0:5" type="1" dataType="11"><Scaling enabled="0" type="0"/><Events enabled="0" source="Alias" severity="1" trigger="0" timestamp="0"/></PSTAlias><PSTAlias name="Stop" itemPath="STAN5.1:1" type="1" dataType="11"><Scaling enabled="0" type="0"/><Events enabled="0" source="Alias" severity="1" trigger="0" timestamp="0"/></PSTAlias><PSTAlias name="Stop_s" itemPath="STAN5.0:1" type="1" dataType="11"><Scaling enabled="0" type="0"/><Events enabled="0" source="Alias" severity="1" trigger="0" timestamp="0"/></PSTAlias></PSTAliasGroup><PSTAliasGroup name="STAN6"><PSTAlias name="Fail" itemPath="STAN6.1:6" type="1" dataType="11"><Scaling enabled="0" type="0"/><Events enabled="0" source="Alias" severity="1" trigger="0" timestamp="0"/></PSTAlias><PSTAlias name="Fail_s" itemPath="STAN6.0:6" type="1" dataType="11"><Scaling enabled="0" type="0"/><Events enabled="0" source="Alias" severity="1" trigger="0" timestamp="0"/></PSTAlias><PSTAlias name="Finish" itemPath="STAN6.1:3" type="1" dataType="11"><Scaling enabled="0" type="0"/><Events enabled="0" source="Alias" severity="1" trigger="0" timestamp="0"/></PSTAlias><PSTAlias name="Finish_s" itemPath="STAN6.0:3" type="1" dataType="11"><Scaling enabled="0" type="0"/><Events enabled="0" source="Alias" severity="1" trigger="0" timestamp="0"/></PSTAlias><PSTAlias name="Help" itemPath="STAN6.1:2" type="1" dataType="11"><Scaling enabled="0" type="0"/><Events enabled="0" source="Alias" severity="1" trigger="0" timestamp="0"/></PSTAlias><PSTAlias name="Help_s" itemPath="STAN6.0:2" type="1" dataType="11"><Scaling enabled="0" type="0"/><Events enabled="0" source="Alias" severity="1" trigger="0" timestamp="0"/></PSTAlias><PSTAlias name="Part1" itemPath="STAN6.1:4" type="1" dataType="11"><Scaling enabled="0" type="0"/><Events enabled="0" source="Alias" severity="1" trigger="0" timestamp="0"/></PSTAlias><PSTAlias name="Part1_s" itemPath="STAN6.0:4" type="1" dataType="11"><Scaling enabled="0" type="0"/><Events enabled="0" source="Alias" severity="1" trigger="0" timestamp="0"/></PSTAlias><PSTAlias name="Part2" itemPath="STAN6.1:5" type="1" dataType="11"><Scaling enabled="0" type="0"/><Events enabled="0" source="Alias" severity="1" trigger="0" timestamp="0"/></PSTAlias><PSTAlias name="Part2_s" itemPath="STAN6.0:5" type="1" dataType="11"><Scaling enabled="0" type="0"/><Events enabled="0" source="Alias" severity="1" trigger="0" timestamp="0"/></PSTAlias><PSTAlias name="Stop" itemPath="STAN6.1:1" type="1" dataType="11"><Scaling enabled="0" type="0"/><Events enabled="0" source="Alias" severity="1" trigger="0" timestamp="0"/></PSTAlias><PSTAlias name="Stop_s" itemPath="STAN6.0:1" type="1" dataType="11"><Scaling enabled="0" type="0"/><Events enabled="0" source="Alias" severity="1" trigger="0" timestamp="0"/></PSTAlias></PSTAliasGroup><PSTAliasGroup name="STAN7"><PSTAlias name="Fail" itemPath="STAN7.1:6" type="1" dataType="11"><Scaling enabled="0" type="0"/><Events enabled="0" source="Alias" severity="1" trigger="0" timestamp="0"/></PSTAlias><PSTAlias name="Fail_s" itemPath="STAN7.0:6" type="1" dataType="11"><Scaling enabled="0" type="0"/><Events enabled="0" source="Alias" severity="1" trigger="0" timestamp="0"/></PSTAlias><PSTAlias name="Finish" itemPath="STAN7.1:3" type="1" dataType="11"><Scaling enabled="0" type="0"/><Events enabled="0" source="Alias" severity="1" trigger="0" timestamp="0"/></PSTAlias><PSTAlias name="Finish_s" itemPath="STAN7.0:3" type="1" dataType="11"><Scaling enabled="0" type="0"/><Events enabled="0" source="Alias" severity="1" trigger="0" timestamp="0"/></PSTAlias><PSTAlias name="Help" itemPath="STAN7.1:2" type="1" dataType="11"><Scaling enabled="0" type="0"/><Events enabled="0" source="Alias" severity="1" trigger="0" timestamp="0"/></PSTAlias><PSTAlias name="Help_s" itemPath="STAN7.0:2" type="1" dataType="11"><Scaling enabled="0" type="0"/><Events enabled="0" source="Alias" severity="1" trigger="0" timestamp="0"/></PSTAlias><PSTAlias name="Part1" itemPath="STAN7.1:4" type="1" dataType="11"><Scaling enabled="0" type="0"/><Events enabled="0" source="Alias" severity="1" trigger="0" timestamp="0"/></PSTAlias><PSTAlias name="Part1_s" itemPath="STAN7.0:4" type="1" dataType="11"><Scaling enabled="0" type="0"/><Events enabled="0" source="Alias" severity="1" trigger="0" timestamp="0"/></PSTAlias><PSTAlias name="Part2" itemPath="STAN7.1:5" type="1" dataType="11"><Scaling enabled="0" type="0"/><Events enabled="0" source="Alias" severity="1" trigger="0" timestamp="0"/></PSTAlias><PSTAlias name="Part2_s" itemPath="STAN7.0:5" type="1" dataType="11"><Scaling enabled="0" type="0"/><Events enabled="0" source="Alias" severity="1" trigger="0" timestamp="0"/></PSTAlias><PSTAlias name="Stop" itemPath="STAN7.1:1" type="1" dataType="11"><Scaling enabled="0" type="0"/><Events enabled="0" source="Alias" severity="1" trigger="0" timestamp="0"/></PSTAlias><PSTAlias name="Stop_s" itemPath="STAN7.0:1" type="1" dataType="11"><Scaling enabled="0" type="0"/><Events enabled="0" source="Alias" severity="1" trigger="0" timestamp="0"/></PSTAlias></PSTAliasGroup><PSTAliasGroup name="STAN8"><PSTAlias name="Fail" itemPath="STAN8.1:6" type="1" dataType="11"><Scaling enabled="0" type="0"/><Events enabled="0" source="Alias" severity="1" trigger="0" timestamp="0"/></PSTAlias><PSTAlias name="Fail_s" itemPath="STAN8.0:6" type="1" dataType="11"><Scaling enabled="0" type="0"/><Events enabled="0" source="Alias" severity="1" trigger="0" timestamp="0"/></PSTAlias><PSTAlias name="Finish" itemPath="STAN8.1:3" type="1" dataType="11"><Scaling enabled="0" type="0"/><Events enabled="0" source="Alias" severity="1" trigger="0" timestamp="0"/></PSTAlias><PSTAlias name="Finish_s" itemPath="STAN8.0:3" type="1" dataType="11"><Scaling enabled="0" type="0"/><Events enabled="0" source="Alias" severity="1" trigger="0" timestamp="0"/></PSTAlias><PSTAlias name="Help" itemPath="STAN8.1:2" type="1" dataType="11"><Scaling enabled="0" type="0"/><Events enabled="0" source="Alias" severity="1" trigger="0" timestamp="0"/></PSTAlias><PSTAlias name="Help_s" itemPath="STAN8.0:2" type="1" dataType="11"><Scaling enabled="0" type="0"/><Events enabled="0" source="Alias" severity="1" trigger="0" timestamp="0"/></PSTAlias><PSTAlias name="Part1" itemPath="STAN8.1:4" type="1" dataType="11"><Scaling enabled="0" type="0"/><Events enabled="0" source="Alias" severity="1" trigger="0" timestamp="0"/></PSTAlias><PSTAlias name="Part1_s" itemPath="STAN8.0:4" type="1" dataType="11"><Scaling enabled="0" type="0"/><Events enabled="0" source="Alias" severity="1" trigger="0" timestamp="0"/></PSTAlias><PSTAlias name="Part2" itemPath="STAN8.1:5" type="1" dataType="11"><Scaling enabled="0" type="0"/><Events enabled="0" source="Alias" severity="1" trigger="0" timestamp="0"/></PSTAlias><PSTAlias name="Part2_s" itemPath="STAN8.0:5" type="1" dataType="11"><Scaling enabled="0" type="0"/><Events enabled="0" source="Alias" severity="1" trigger="0" timestamp="0"/></PSTAlias><PSTAlias name="Stop" itemPath="STAN8.1:1" type="1" dataType="11"><Scaling enabled="0" type="0"/><Events enabled="0" source="Alias" severity="1" trigger="0" timestamp="0"/></PSTAlias><PSTAlias name="Stop_s" itemPath="STAN8.0:1" type="1" dataType="11"><Scaling enabled="0" type="0"/><Events enabled="0" source="Alias" severity="1" trigger="0" timestamp="0"/></PSTAlias></PSTAliasGroup><PSTAliasGroup name="STAN_FA5A"><PSTAlias name="Fail" itemPath="STAN_FA5A.1:6" type="1" dataType="11"><Scaling enabled="0" type="0"/><Events enabled="0" source="Alias" severity="1" trigger="0" timestamp="0"/></PSTAlias><PSTAlias name="Fail_s" itemPath="STAN_FA5A.0:6" type="1" dataType="11"><Scaling enabled="0" type="0"/><Events enabled="0" source="Alias" severity="1" trigger="0" timestamp="0"/></PSTAlias><PSTAlias name="Finish" itemPath="STAN_FA5A.1:3" type="1" dataType="11"><Scaling enabled="0" type="0"/><Events enabled="0" source="Alias" severity="1" trigger="0" timestamp="0"/></PSTAlias><PSTAlias name="Finish_s" itemPath="STAN_FA5A.0:3" type="1" dataType="11"><Scaling enabled="0" type="0"/><Events enabled="0" source="Alias" severity="1" trigger="0" timestamp="0"/></PSTAlias><PSTAlias name="Help" itemPath="STAN_FA5A.1:2" type="1" dataType="11"><Scaling enabled="0" type="0"/><Events enabled="0" source="Alias" severity="1" trigger="0" timestamp="0"/></PSTAlias><PSTAlias name="Help_s" itemPath="STAN_FA5A.0:2" type="1" dataType="11"><Scaling enabled="0" type="0"/><Events enabled="0" source="Alias" severity="1" trigger="0" timestamp="0"/></PSTAlias><PSTAlias name="Part1" itemPath="STAN_FA5A.1:4" type="1" dataType="11"><Scaling enabled="0" type="0"/><Events enabled="0" source="Alias" severity="1" trigger="0" timestamp="0"/></PSTAlias><PSTAlias name="Part1_s" itemPath="STAN_FA5A.0:4" type="1" dataType="11"><Scaling enabled="0" type="0"/><Events enabled="0" source="Alias" severity="1" trigger="0" timestamp="0"/></PSTAlias><PSTAlias name="Part2" itemPath="STAN_FA5A.1:5" type="1" dataType="11"><Scaling enabled="0" type="0"/><Events enabled="0" source="Alias" severity="1" trigger="0" timestamp="0"/></PSTAlias><PSTAlias name="Part2_s" itemPath="STAN_FA5A.0:5" type="1" dataType="11"><Scaling enabled="0" type="0"/><Events enabled="0" source="Alias" severity="1" trigger="0" timestamp="0"/></PSTAlias><PSTAlias name="Stop" itemPath="STAN_FA5A.1:1" type="1" dataType="11"><Scaling enabled="0" type="0"/><Events enabled="0" source="Alias" severity="1" trigger="0" timestamp="0"/></PSTAlias><PSTAlias name="Stop_s" itemPath="STAN_FA5A.0:1" type="1" dataType="11"><Scaling enabled="0" type="0"/><Events enabled="0" source="Alias" severity="1" trigger="0" timestamp="0"/></PSTAlias></PSTAliasGroup><PSTAliasGroup name="STAN_FI"><PSTAlias name="Fail" itemPath="STAN_FI.1:6" type="1" dataType="11"><Scaling enabled="0" type="0"/><Events enabled="0" source="Alias" severity="1" trigger="0" timestamp="0"/></PSTAlias><PSTAlias name="Fail_s" itemPath="STAN_FI.0:6" type="1" dataType="11"><Scaling enabled="0" type="0"/><Events enabled="0" source="Alias" severity="1" trigger="0" timestamp="0"/></PSTAlias><PSTAlias name="Finish" itemPath="STAN_FI.1:3" type="1" dataType="11"><Scaling enabled="0" type="0"/><Events enabled="0" source="Alias" severity="1" trigger="0" timestamp="0"/></PSTAlias><PSTAlias name="Finish_s" itemPath="STAN_FI.0:3" type="1" dataType="11"><Scaling enabled="0" type="0"/><Events enabled="0" source="Alias" severity="1" trigger="0" timestamp="0"/></PSTAlias><PSTAlias name="Help" itemPath="STAN_FI.1:2" type="1" dataType="11"><Scaling enabled="0" type="0"/><Events enabled="0" source="Alias" severity="1" trigger="0" timestamp="0"/></PSTAlias><PSTAlias name="Help_s" itemPath="STAN_FI.0:2" type="1" dataType="11"><Scaling enabled="0" type="0"/><Events enabled="0" source="Alias" severity="1" trigger="0" timestamp="0"/></PSTAlias><PSTAlias name="Part1" itemPath="STAN_FI.1:4" type="1" dataType="11"><Scaling enabled="0" type="0"/><Events enabled="0" source="Alias" severity="1" trigger="0" timestamp="0"/></PSTAlias><PSTAlias name="Part1_s" itemPath="STAN_FI.0:4" type="1" dataType="11"><Scaling enabled="0" type="0"/><Events enabled="0" source="Alias" severity="1" trigger="0" timestamp="0"/></PSTAlias><PSTAlias name="Part2" itemPath="STAN_FI.1:5" type="1" dataType="11"><Scaling enabled="0" type="0"/><Events enabled="0" source="Alias" severity="1" trigger="0" timestamp="0"/></PSTAlias><PSTAlias name="Part2_s" itemPath="STAN_FI.0:5" type="1" dataType="11"><Scaling enabled="0" type="0"/><Events enabled="0" source="Alias" severity="1" trigger="0" timestamp="0"/></PSTAlias><PSTAlias name="Stop" itemPath="STAN_FI.1:1" type="1" dataType="11"><Scaling enabled="0" type="0"/><Events enabled="0" source="Alias" severity="1" trigger="0" timestamp="0"/></PSTAlias><PSTAlias name="Stop_s" itemPath="STAN_FI.0:1" type="1" dataType="11"><Scaling enabled="0" type="0"/><Events enabled="0" source="Alias" severity="1" trigger="0" timestamp="0"/></PSTAlias></PSTAliasGroup><PSTAliasGroup name="STAN_PDI1"><PSTAlias name="Fail" itemPath="STAN_PDI1.1:6" type="1" dataType="11"><Scaling enabled="0" type="0"/><Events enabled="0" source="Alias" severity="1" trigger="0" timestamp="0"/></PSTAlias><PSTAlias name="Fail_s" itemPath="STAN_PDI1.0:6" type="1" dataType="11"><Scaling enabled="0" type="0"/><Events enabled="0" source="Alias" severity="1" trigger="0" timestamp="0"/></PSTAlias><PSTAlias name="Finish" itemPath="STAN_PDI1.1:3" type="1" dataType="11"><Scaling enabled="0" type="0"/><Events enabled="0" source="Alias" severity="1" trigger="0" timestamp="0"/></PSTAlias><PSTAlias name="Finish_s" itemPath="STAN_PDI1.0:3" type="1" dataType="11"><Scaling enabled="0" type="0"/><Events enabled="0" source="Alias" severity="1" trigger="0" timestamp="0"/></PSTAlias><PSTAlias name="Help" itemPath="STAN_PDI1.1:2" type="1" dataType="11"><Scaling enabled="0" type="0"/><Events enabled="0" source="Alias" severity="1" trigger="0" timestamp="0"/></PSTAlias><PSTAlias name="Help_s" itemPath="STAN_PDI1.0:2" type="1" dataType="11"><Scaling enabled="0" type="0"/><Events enabled="0" source="Alias" severity="1" trigger="0" timestamp="0"/></PSTAlias><PSTAlias name="Part1" itemPath="STAN_PDI1.1:4" type="1" dataType="11"><Scaling enabled="0" type="0"/><Events enabled="0" source="Alias" severity="1" trigger="0" timestamp="0"/></PSTAlias><PSTAlias name="Part1_s" itemPath="STAN_PDI1.0:4" type="1" dataType="11"><Scaling enabled="0" type="0"/><Events enabled="0" source="Alias" severity="1" trigger="0" timestamp="0"/></PSTAlias><PSTAlias name="Part2" itemPath="STAN_PDI1.1:5" type="1" dataType="11"><Scaling enabled="0" type="0"/><Events enabled="0" source="Alias" severity="1" trigger="0" timestamp="0"/></PSTAlias><PSTAlias name="Part2_s" itemPath="STAN_PDI1.0:5" type="1" dataType="11"><Scaling enabled="0" type="0"/><Events enabled="0" source="Alias" severity="1" trigger="0" timestamp="0"/></PSTAlias><PSTAlias name="Stop" itemPath="STAN_PDI1.1:1" type="1" dataType="11"><Scaling enabled="0" type="0"/><Events enabled="0" source="Alias" severity="1" trigger="0" timestamp="0"/></PSTAlias><PSTAlias name="Stop_s" itemPath="STAN_PDI1.0:1" type="1" dataType="11"><Scaling enabled="0" type="0"/><Events enabled="0" source="Alias" severity="1" trigger="0" timestamp="0"/></PSTAlias></PSTAliasGroup><PSTAliasGroup name="STAN_PDI2"><PSTAlias name="Fail" itemPath="STAN_PDI2.1:6" type="1" dataType="11"><Scaling enabled="0" type="0"/><Events enabled="0" source="Alias" severity="1" trigger="0" timestamp="0"/></PSTAlias><PSTAlias name="Fail_s" itemPath="STAN_PDI2.0:6" type="1" dataType="11"><Scaling enabled="0" type="0"/><Events enabled="0" source="Alias" severity="1" trigger="0" timestamp="0"/></PSTAlias><PSTAlias name="Finish" itemPath="STAN_PDI2.1:3" type="1" dataType="11"><Scaling enabled="0" type="0"/><Events enabled="0" source="Alias" severity="1" trigger="0" timestamp="0"/></PSTAlias><PSTAlias name="Finish_s" itemPath="STAN_PDI2.0:3" type="1" dataType="11"><Scaling enabled="0" type="0"/><Events enabled="0" source="Alias" severity="1" trigger="0" timestamp="0"/></PSTAlias><PSTAlias name="Help" itemPath="STAN_PDI2.1:2" type="1" dataType="11"><Scaling enabled="0" type="0"/><Events enabled="0" source="Alias" severity="1" trigger="0" timestamp="0"/></PSTAlias><PSTAlias name="Help_s" itemPath="STAN_PDI2.0:2" type="1" dataType="11"><Scaling enabled="0" type="0"/><Events enabled="0" source="Alias" severity="1" trigger="0" timestamp="0"/></PSTAlias><PSTAlias name="Part1" itemPath="STAN_PDI2.1:4" type="1" dataType="11"><Scaling enabled="0" type="0"/><Events enabled="0" source="Alias" severity="1" trigger="0" timestamp="0"/></PSTAlias><PSTAlias name="Part1_s" itemPath="STAN_PDI2.0:4" type="1" dataType="11"><Scaling enabled="0" type="0"/><Events enabled="0" source="Alias" severity="1" trigger="0" timestamp="0"/></PSTAlias><PSTAlias name="Part2" itemPath="STAN_PDI2.1:5" type="1" dataType="11"><Scaling enabled="0" type="0"/><Events enabled="0" source="Alias" severity="1" trigger="0" timestamp="0"/></PSTAlias><PSTAlias name="Part2_s" itemPath="STAN_PDI2.0:5" type="1" dataType="11"><Scaling enabled="0" type="0"/><Events enabled="0" source="Alias" severity="1" trigger="0" timestamp="0"/></PSTAlias><PSTAlias name="Stop" itemPath="STAN_PDI2.1:1" type="1" dataType="11"><Scaling enabled="0" type="0"/><Events enabled="0" source="Alias" severity="1" trigger="0" timestamp="0"/></PSTAlias><PSTAlias name="Stop_s" itemPath="STAN_PDI2.0:1" type="1" dataType="11"><Scaling enabled="0" type="0"/><Events enabled="0" source="Alias" severity="1" trigger="0" timestamp="0"/></PSTAlias></PSTAliasGroup><PSTAliasGroup name="STAN_TIP"><PSTAlias name="Fail" itemPath="STAN_TIP.1:6" type="1" dataType="11"><Scaling enabled="0" type="0"/><Events enabled="0" source="Alias" severity="1" trigger="0" timestamp="0"/></PSTAlias><PSTAlias name="Fail_s" itemPath="STAN_TIP.0:6" type="1" dataType="11"><Scaling enabled="0" type="0"/><Events enabled="0" source="Alias" severity="1" trigger="0" timestamp="0"/></PSTAlias><PSTAlias name="Finish" itemPath="STAN_TIP.1:3" type="1" dataType="11"><Scaling enabled="0" type="0"/><Events enabled="0" source="Alias" severity="1" trigger="0" timestamp="0"/></PSTAlias><PSTAlias name="Finish_s" itemPath="STAN_TIP.0:3" type="1" dataType="11"><Scaling enabled="0" type="0"/><Events enabled="0" source="Alias" severity="1" trigger="0" timestamp="0"/></PSTAlias><PSTAlias name="Help" itemPath="STAN_TIP.1:2" type="1" dataType="11"><Scaling enabled="0" type="0"/><Events enabled="0" source="Alias" severity="1" trigger="0" timestamp="0"/></PSTAlias><PSTAlias name="Help_s" itemPath="STAN_TIP.0:2" type="1" dataType="11"><Scaling enabled="0" type="0"/><Events enabled="0" source="Alias" severity="1" trigger="0" timestamp="0"/></PSTAlias><PSTAlias name="Part1" itemPath="STAN_TIP.1:4" type="1" dataType="11"><Scaling enabled="0" type="0"/><Events enabled="0" source="Alias" severity="1" trigger="0" timestamp="0"/></PSTAlias><PSTAlias name="Part1_s" itemPath="STAN_TIP.0:4" type="1" dataType="11"><Scaling enabled="0" type="0"/><Events enabled="0" source="Alias" severity="1" trigger="0" timestamp="0"/></PSTAlias><PSTAlias name="Part2" itemPath="STAN_TIP.1:5" type="1" dataType="11"><Scaling enabled="0" type="0"/><Events enabled="0" source="Alias" severity="1" trigger="0" timestamp="0"/></PSTAlias><PSTAlias name="Part2_s" itemPath="STAN_TIP.0:5" type="1" dataType="11"><Scaling enabled="0" type="0"/><Events enabled="0" source="Alias" severity="1" trigger="0" timestamp="0"/></PSTAlias><PSTAlias name="Stop" itemPath="STAN_TIP.1:1" type="1" dataType="11"><Scaling enabled="0" type="0"/><Events enabled="0" source="Alias" severity="1" trigger="0" timestamp="0"/></PSTAlias><PSTAlias name="Stop_s" itemPath="STAN_TIP.0:1" type="1" dataType="11"><Scaling enabled="0" type="0"/><Events enabled="0" source="Alias" severity="1" trigger="0" timestamp="0"/></PSTAlias></PSTAliasGroup></PSTAliasGroup></Matrikon.OPC.Modbus>
